README.rst
setup.py
bin/fedcred
fedcred/__init__.py
fedcred/common.py
fedcred.egg-info/PKG-INFO
fedcred.egg-info/SOURCES.txt
fedcred.egg-info/dependency_links.txt
fedcred.egg-info/requires.txt
fedcred.egg-info/top_level.txt
fedcred/providers/__init__.py
fedcred/providers/adfs.py
fedcred/providers/okta.py