Metadata-Version: 1.0
Name: fedcred
Version: 0.0.1
Summary: Get AWS API Credentials When using an Identity Provider/Federation
Home-page: https://github.com/broamski/aws-fedcred
Author: Brian Nuszkowski
Author-email: nuszkowski@protonmail.com
License: UNKNOWN
Platform: UNKNOWN
